coala_html-0.3.1.dist-info/DESCRIPTION.rst
coala_html-0.3.1.dist-info/METADATA
coala_html-0.3.1.dist-info/RECORD
coala_html-0.3.1.dist-info/WHEEL
coala_html-0.3.1.dist-info/entry_points.txt
coala_html-0.3.1.dist-info/metadata.json
coala_html-0.3.1.dist-info/top_level.txt
coalahtml/Constants.py
coalahtml/__init__.py
coalahtml/coala_html.py
coalahtml/helper.py
coalahtml/tree.py
coalahtml/_coalahtml/bower.json
coalahtml/_coalahtml/index.html
coalahtml/_coalahtml/app/app.js
coalahtml/_coalahtml/app/controllers/directives.js
coalahtml/_coalahtml/app/controllers/files.js
coalahtml/_coalahtml/app/controllers/logs.js
coalahtml/_coalahtml/app/controllers/main.js
coalahtml/_coalahtml/app/styles/files.css
coalahtml/_coalahtml/app/styles/logs.css
coalahtml/_coalahtml/app/styles/main.css
coalahtml/_coalahtml/app/views/files.html
coalahtml/_coalahtml/app/views/logs.html
coalahtml/_coalahtml/app/views/main.html
coalahtml/_coalahtml/data/Constants.json
coalahtml/_coalahtml/data/coala.json
